day01/All_Zeros_Detector/all_zeros_detector.v
module all_zeros_detector(
  input [7:0]a, 
  output result
);
  
  assign result = ~(|a);
  
endmodule

day01/All_Zeros_Detector/tb_all_zeros_detector.v
module tb_all_zeros_detector;
  
  reg [7:0]a;
  wire result;
  
  all_zeros_detector dut(.a(a), .result(result));
  
  initial begin
    $dumpfile("allzerosdetector.vcd");
    $dumpvars(0);
  end
  
  initial begin   
    $monitor("a = %b | Result = %b", a, result);
  end

  initial begin 	
    a = 8'd0; 
    #10 a = 8'd1;
    #10 a = 8'd2;
    #10 a = 8'd3;
    #10 a = 8'd4;
    #10 a = 8'd6;
    #10 a = 8'd7;
    #10 a = 8'd15;
    #10 a = 8'd255;
    #10 a = 8'd127;
    #10 a = 8'd60;
	#10 a = 8'd0;
    #50 $finish;
  end
endmodule

day01/All_Zeros_Detector/allzerosdetector.vcd
$date
	Thu Mar 26 07:03:20 2026
$end
$version
	Icarus Verilog
$end
$timescale
	1s
$end
$scope module tb_all_zeros_detector $end
$var wire 1 ! result $end
$var reg 8 " a [7:0] $end
$scope module dut $end
$var wire 8 # a [7:0] $end
$var wire 1 ! result $end
$upscope $end
$upscope $end
$enddefinitions $end
$comment Show the parameter values. $end
$dumpall
$end
#0
$dumpvars
b0 #
b0 "
1!
$end
#10
0!
b1 "
b1 #
#20
b10 "
b10 #
#30
b11 "
b11 #
#40
b100 "
b100 #
#50
b110 "
b110 #
#60
b111 "
b111 #
#70
b1111 "
b1111 #
#80
b11111111 "
b11111111 #
#90
b1111111 "
b1111111 #
#100
b111100 "
b111100 #
#110
1!
b0 "
b0 #
