day01/Full_Adder/fa.v
module fa(
input wire a, 
input wire b, 
input wire cin,
output wire sum, 
output wire carry_out
);

assign sum = a ^ b ^ cin;
assign carry_out =(a && b) ||(b && cin) || (cin && a);

endmodule

day01/Full_Adder/tb_fa.v
module tb_fa;
  reg a, b, cin;
  wire sum, carry_out;

  fa UUT (.a(a), .b(b), .cin(cin), .sum(sum), .carry_out(carry_out));

  initial begin
    $dumpfile("fulladder.vcd");

    $dumpvars(0, tb_fa);

    $display("+++++++++++++++++++++++++++++++++++++++++++++++++++++++++++++++++++++++++++++++++++++++++++");
    $display("+++++++++++++++++++++++++++++++++++Full-Adder Simulation+++++++++++++++++++++++++++++++++++");
    $display("+++++++++++++++++++++++++++++++++++++++++++++++++++++++++++++++++++++++++++++++++++++++++++");

    $monitor("Time = %0t | a = %b | b = %b | cin = %b | sum = %b | carry_out = %b", $time, a, b, cin, sum, carry_out);
	
	a = 1'b0; b = 1'b0; cin = 1'b0;
	#10 a = 1'b0; b = 1'b0; cin = 1'b1;
	#10 a = 1'b0; b = 1'b1; cin = 1'b0;
	#10 a = 1'b0; b = 1'b1; cin = 1'b1;
	#10 a = 1'b1; b = 1'b0; cin = 1'b0;
	#10 a = 1'b1; b = 1'b0; cin = 1'b1;
	#10 a = 1'b1; b = 1'b1; cin = 1'b0;
	#10 a = 1'b1; b = 1'b1; cin = 1'b1;

	#30 $finish;
    end

endmodule

day01/Full_Adder/fulladder.vcd
$date
	Wed Mar 25 03:52:54 2026
$end
$version
	Icarus Verilog
$end
$timescale
	1s
$end
$scope module tb_fa $end
$var wire 1 ! sum $end
$var wire 1 " carry_out $end
$var reg 1 # a $end
$var reg 1 $ b $end
$var reg 1 % cin $end
$scope module UUT $end
$var wire 1 # a $end
$var wire 1 $ b $end
$var wire 1 " carry_out $end
$var wire 1 % cin $end
$var wire 1 ! sum $end
$upscope $end
$upscope $end
$enddefinitions $end
$comment Show the parameter values. $end
$dumpall
$end
#0
$dumpvars
0%
0$
0#
0"
0!
$end
#10
1!
1%
#20
0%
1$
#30
1"
0!
1%
#40
0"
1!
0%
0$
1#
#50
1"
0!
1%
#60
0%
1$
#70
1!
1%
