day01/Two_to_One_MUX/two_to_one_MUX.v
module two_to_one_MUX (
  input wire i0,
  input wire i1, 
  input wire sel,
  output wire y
);
  
  assign y = (sel == 1'b0) ? i0 : i1;
  
endmodule

day01/Two_to_One_MUX/tb_two_to_one_MUX.v
module tb_two_to_one_MUX;
  reg i0, i1, sel;
  wire y;
  
  two_to_one_MUX DUT (.i0(i0), .i1(i1), .sel(sel), .y(y));
  
  initial begin 
    $display("=============================================================");
    
    $display("=====================2:1 MULTIPLEXER=========================");
    
    $display("=============================================================");
    
    $dumpfile("twotooneMUX.vcd");
    
    $dumpvars(0);
    
    $monitor ("i0 = %b | i1 = %b | sel = %b | y = %b", i0, i1, sel, y);
    
    i0 = 1'b0; i1 = 1'b0; sel = 1'b0;
    
    #10 i0 = 1'b0; i1 = 1'b0; sel = 1'b1;
    #10 i0 = 1'b0; i1 = 1'b1; sel = 1'b0;
    #10 i0 = 1'b0; i1 = 1'b1; sel = 1'b1;
    #10 i0 = 1'b1; i1 = 1'b0; sel = 1'b0;
    #10 i0 = 1'b1; i1 = 1'b0; sel = 1'b1;
    #10 i0 = 1'b1; i1 = 1'b1; sel = 1'b0;
    #10 i0 = 1'b1; i1 = 1'b1; sel = 1'b1;
    
    #10 i0 = 1'b0; i1 = 1'b0; sel = 1'b0;
    
    #10 i0 = 1'b0; i1 = 1'b0; sel = 1'b1;
    #10 i0 = 1'b0; i1 = 1'b1; sel = 1'b0;
    #10 i0 = 1'b0; i1 = 1'b1; sel = 1'b1;
    #10 i0 = 1'b1; i1 = 1'b0; sel = 1'b0;
    #10 i0 = 1'b1; i1 = 1'b0; sel = 1'b1;
    #10 i0 = 1'b1; i1 = 1'b1; sel = 1'b0;
    #10 i0 = 1'b1; i1 = 1'b1; sel = 1'b1;
    
    #40 $finish;
    
  end
  
endmodule

day01/Two_to_One_MUX/twotooneMUX.vcd
$date
	Thu Mar 26 06:46:43 2026
$end
$version
	Icarus Verilog
$end
$timescale
	1s
$end
$scope module tb_two_to_one_MUX $end
$var wire 1 ! y $end
$var reg 1 " i0 $end
$var reg 1 # i1 $end
$var reg 1 $ sel $end
$scope module DUT $end
$var wire 1 " i0 $end
$var wire 1 # i1 $end
$var wire 1 $ sel $end
$var wire 1 ! y $end
$upscope $end
$upscope $end
$enddefinitions $end
$comment Show the parameter values. $end
$dumpall
$end
#0
$dumpvars
0$
0#
0"
0!
$end
#10
1$
#20
0!
0$
1#
#30
1!
1$
#40
1!
0$
0#
1"
#50
0!
1$
#60
1!
0$
1#
#70
1$
#80
0!
0$
0#
0"
#90
1$
#100
0!
0$
1#
#110
1!
1$
#120
1!
0$
0#
1"
#130
0!
1$
#140
1!
0$
1#
#150
1$
