day01/Full_Subtractor/full_subtractor.v
module full_subtractor_gatelevel (
input wire a, 
input wire b,
input wire bin, 
output wire difference_gl, 
output wire borrow_out_gl

);

// Gate-Level Modeling: 
wire xor_1, and_1, and_2, not_1, a_n, xnor_1;
xor xor1 (xor_1, a, b);
xor xor2 (difference_gl, xor_1, bin);
not not1 (a_n, a);
and and1 (and_1, a_n, b);
not not2 (not_1, xor_1);
and and2 (and_2, not_1, bin);
or or2 (borrow_out_gl, and_1, and_2);

endmodule


module full_subtractor_dataflow (
input wire a,
input wire b,
input wire bin,
output wire difference_df,
output wire borrow_out_df

);


// Dataflow Modeling: 

assign difference_df = a ^ b ^ bin;

assign borrow_out_df =(!a & b) | (!a & bin) | (b & bin);


endmodule


module full_subtractor_behavioral (
input wire a,
input wire b,
input wire bin,
output reg difference_beh,
output reg borrow_out_beh

);


// Behavioral Modeling

always @(*) begin 
  
  difference_beh = a ^ b ^ bin; 

  borrow_out_beh = (!a & b) | (!a & bin) | (b & bin);

 end 

endmodule

day01/Full_Subtractor/tb_full_subtractor.v
`timescale 1ns/1ps

module tb_full_subtractor;

reg a, b, bin;

wire difference_gl, difference_df, difference_beh, borrow_out_gl, borrow_out_df, borrow_out_beh;

full_subtractor_gatelevel dut_gl (.a(a), .b(b), .bin(bin), .difference_gl(difference_gl), .borrow_out_gl(borrow_out_gl));
full_subtractor_dataflow dut_df (.a(a), .b(b), .bin(bin), .difference_df(difference_df), .borrow_out_df(borrow_out_df));
full_subtractor_behavioral dut_beh (.a(a), .b(b), .bin(bin), .difference_beh(difference_beh), .borrow_out_beh(borrow_out_beh));
initial begin 

$dumpfile ("fullsubtractor.vcd");

$dumpvars(0);

end

initial begin 
$display("=====================================================================================================================");

$display("++++++++++++++++++++++++++++++++++++++++++++++Full Subtractor Result+++++++++++++++++++++++++++++++++++++++++++++++++");

$display("=====================================================================================================================");

$monitor("Time = %0t | a = %b | b = %b | bin = %b | difference_gl = %b | borrow_out_gl = %b | difference_df = %b | borrow_out_df = %b | difference_beh = %b | borrow_out_beh = %b", $time, a, b, bin, difference_gl, borrow_out_gl, difference_df, borrow_out_df, difference_beh, borrow_out_beh);


end

initial begin 

a = 1'b0; b = 1'b0; bin = 1'b0;

#10 a = 1'b0; b = 1'b0; bin = 1'b1;

#10 a = 1'b0; b = 1'b1; bin = 1'b0;

#10 a = 1'b0; b = 1'b1; bin = 1'b1;

#10 a = 1'b1; b = 1'b0; bin = 1'b0; 

#10 a = 1'b1; b = 1'b0; bin = 1'b1;

#10 a = 1'b1; b = 1'b1; bin = 1'b0;

#10 a = 1'b1; b = 1'b1; bin = 1'b1;

#10 a = 1'b0; b = 1'b0; bin = 1'b0;

#10 a = 1'b0; b = 1'b0; bin = 1'b1;

#10 a = 1'b0; b = 1'b1; bin = 1'b0;

#10 a = 1'b0; b = 1'b1; bin = 1'b1;

#10 a = 1'b1; b = 1'b0; bin = 1'b0;

#10 a = 1'b1; b = 1'b0; bin = 1'b1;

#10 a = 1'b1; b = 1'b1; bin = 1'b0;

#10 a = 1'b1; b = 1'b1; bin = 1'b1;

#50 $finish;

end

endmodule

day01/Full_Subtractor/fullsubtractor.vcd
$date
	Thu Mar 26 17:04:23 2026
$end
$version
	Icarus Verilog
$end
$timescale
	1ps
$end
$scope module tb_full_subtractor $end
$var wire 1 ! difference_gl $end
$var wire 1 " difference_df $end
$var wire 1 # difference_beh $end
$var wire 1 $ borrow_out_gl $end
$var wire 1 % borrow_out_df $end
$var wire 1 & borrow_out_beh $end
$var reg 1 ' a $end
$var reg 1 ( b $end
$var reg 1 ) bin $end
$scope module dut_beh $end
$var wire 1 ' a $end
$var wire 1 ( b $end
$var wire 1 ) bin $end
$var reg 1 & borrow_out_beh $end
$var reg 1 # difference_beh $end
$upscope $end
$scope module dut_df $end
$var wire 1 ' a $end
$var wire 1 ( b $end
$var wire 1 ) bin $end
$var wire 1 % borrow_out_df $end
$var wire 1 " difference_df $end
$upscope $end
$scope module dut_gl $end
$var wire 1 ' a $end
$var wire 1 * a_n $end
$var wire 1 + and_1 $end
$var wire 1 , and_2 $end
$var wire 1 ( b $end
$var wire 1 ) bin $end
$var wire 1 $ borrow_out_gl $end
$var wire 1 ! difference_gl $end
$var wire 1 - not_1 $end
$var wire 1 . xor_1 $end
$upscope $end
$upscope $end
$enddefinitions $end
$comment Show the parameter values. $end
$dumpall
$end
#0
$dumpvars
0.
1-
0,
0+
1*
0)
0(
0'
0&
0%
0$
0#
0"
0!
$end
#10000
1%
1$
1&
1#
1"
1!
1,
1)
#20000
0-
0,
1.
1+
0)
1(
#30000
0#
0"
0!
1)
#40000
0%
0$
1"
1!
0+
0&
1#
0*
0)
0(
1'
#50000
0#
0"
0!
1)
#60000
1-
0.
0)
1(
#70000
1%
1$
1&
1#
1"
1!
1,
1)
#80000
0$
0%
0"
0!
0,
0&
0#
1*
0)
0(
0'
#90000
1%
1$
1&
1#
1"
1!
1,
1)
#100000
0-
0,
1.
1+
0)
1(
#110000
0#
0"
0!
1)
#120000
0%
0$
1"
1!
0+
0&
1#
0*
0)
0(
1'
#130000
0#
0"
0!
1)
#140000
1-
0.
0)
1(
#150000
1%
1$
1&
1#
1"
1!
1,
1)
